dict_path/__init__.py
dict_path-1.1.1.dist-info/LICENSE
dict_path-1.1.1.dist-info/METADATA
dict_path-1.1.1.dist-info/WHEEL
dict_path-1.1.1.dist-info/top_level.txt
dict_path-1.1.1.dist-info/RECORD
