Metadata-Version: 2.1
Name: dict-path
Version: 1.1.1
Summary: Python library to work with complicated nested dict
Home-page: https://github.com/maztohir/python-nested-dict
Author: Muhamad Tohir
Author-email: maztohir@gmail.com
License: UNKNOWN
Project-URL: Bug Tracker, https://github.com/maztohir/python-nested-dict/issues
Platform: UNKNOWN
Classifier: Programming Language :: Python :: 3
Classifier: License :: OSI Approved :: MIT License
Classifier: Operating System :: OS Independent
Requires-Python: >=3.6
License-File: LICENSE
